{
  "appPageId" : "a8caf1c7-f6fb-4bd9-a39d-73702775e7ef",
  "componentName" : "siteforce:sldsOneColLayout",
  "id" : "8b15eaac-7590-4d71-a1ee-0768e987f04f",
  "label" : "Account Management",
  "regions" : [ {
    "id" : "e899305d-c273-4b46-8d3e-3b53a47a1800",
    "regionName" : "header",
    "type" : "region"
  }, {
    "components" : [ {
      "componentAttributes" : {
        "tabsetConfig" : {
          "UUID" : "17be92cd-ec93-4fec-b36e-eef534702ab9",
          "activeTab" : "tab1",
          "tabs" : [ {
            "UUID" : "f193f986-c677-4840-be10-6b98bdea33c0",
            "allowGuestUser" : false,
            "locked" : false,
            "seedComponents" : [ {
              "attributes" : {
                "customTitle" : "Members",
                "parentRecordId" : "{!CurrentUser.accountId}",
                "relatedListName" : "Users",
                "showBreadCrumbs" : "false",
                "showCustomTitle" : "true",
                "showManualRefreshButton" : "false",
                "showRowNumbers" : "false"
              },
              "fqn" : "forceCommunity:relatedList"
            } ],
            "tabKey" : "tab1",
            "tabName" : "Members"
          }, {
            "UUID" : "de8c7a1c-b757-49c3-b709-a6421fb3d3f8",
            "allowGuestUser" : false,
            "locked" : false,
            "seedComponents" : [ {
              "attributes" : {
                "recordId" : "{!CurrentUser.accountId}"
              },
              "fqn" : "forceCommunity:accountBrandRecord"
            } ],
            "tabKey" : "tab2",
            "tabName" : "Branding"
          } ],
          "useOverflowMenu" : false
        }
      },
      "componentName" : "forceCommunity:tabset",
      "id" : "17be92cd-ec93-4fec-b36e-eef534702ab9",
      "regions" : [ {
        "components" : [ {
          "componentAttributes" : {
            "customTitle" : "Members",
            "parentRecordId" : "{!CurrentUser.accountId}",
            "relatedListName" : "Users",
            "showBreadCrumbs" : false,
            "showCustomTitle" : true,
            "showManualRefreshButton" : false,
            "showRowNumbers" : false
          },
          "componentName" : "forceCommunity:relatedList",
          "id" : "5822ef12-f3fd-4cd9-835c-0d0cff7895e1",
          "renditionMap" : { },
          "type" : "component"
        } ],
        "id" : "f193f986-c677-4840-be10-6b98bdea33c0",
        "regionLabel" : "Members",
        "regionName" : "tab1",
        "renditionMap" : { },
        "type" : "region"
      }, {
        "components" : [ {
          "componentAttributes" : {
            "recordId" : "{!CurrentUser.accountId}"
          },
          "componentName" : "forceCommunity:accountBrandRecord",
          "id" : "52d700b6-2725-4f1a-9950-abc15ead5932",
          "renditionMap" : { },
          "type" : "component"
        } ],
        "id" : "de8c7a1c-b757-49c3-b709-a6421fb3d3f8",
        "regionLabel" : "Branding",
        "regionName" : "tab2",
        "renditionMap" : { },
        "type" : "region"
      } ],
      "renderPriority" : "NEUTRAL",
      "renditionMap" : { },
      "type" : "component"
    } ],
    "id" : "8343d46f-66f5-4d2f-9569-b14a2b9b5a89",
    "regionName" : "content",
    "type" : "region"
  }, {
    "id" : "1e171f1e-64fd-45c1-b4ed-1e85bb41c773",
    "regionName" : "footer",
    "type" : "region"
  }, {
    "components" : [ {
      "componentAttributes" : {
        "customHeadTags" : "",
        "description" : "",
        "title" : "Account Management"
      },
      "componentName" : "forceCommunity:seoAssistant",
      "id" : "8cf8fd63-fc3f-491d-bd78-e9b0d4e47ec5",
      "renditionMap" : { },
      "type" : "component"
    } ],
    "id" : "5ad1cc76-70cd-4f1e-8b93-e4bcd3828b08",
    "regionName" : "sfdcHiddenRegion",
    "type" : "region"
  } ],
  "themeLayoutType" : "Inner",
  "type" : "view",
  "viewType" : "account-management"
}